.gitignore
CODE_OF_CONDUCT.md
LICENSE
MANIFEST.in
README.md
pyproject.toml
requirements-dev.txt
requirements.txt
setup.cfg
setup.py
/home/anonimous/Documents/Projects/yafl/src/yaflpy/yaflpy.c
doc/AdaptiveCorrection.pdf
doc/C-Manual.md
doc/Python-Manual.md
doc/UsingEKFTricksWithSPKF.pdf
doc/src/AdaptiveCorrection.ipynb
doc/src/UsingEKFTricksWithSPKF.ipynb
doc/src/scratchpad.ipynb
src/yafl.c
src/yafl.h
src/yafl_math.c
src/yafl_math.h
src/yaflpy/immconst.c
src/yaflpy/yafl_config.h
src/yaflpy/yaflpy.c
src/yaflpy/yaflpy.pyx
src/yaflpy/yaflpy.pyxbld
tests/projects/yafl_hdf_tests.workspace
tests/projects/ada_bierman/hdf5_test.cbp
tests/projects/ada_joseph/hdf5_test.cbp
tests/projects/ada_rob_bierman/hdf5_test.cbp
tests/projects/ada_rob_joseph/hdf5_test.cbp
tests/projects/ada_rob_ukf_bierman/hdf5_test.cbp
tests/projects/ada_ukf/hdf5_test.cbp
tests/projects/ada_ukf_bierman/hdf5_test.cbp
tests/projects/bierman/hdf5_test.cbp
tests/projects/imm/hdf5_test.cbp
tests/projects/joseph/hdf5_test.cbp
tests/projects/rob_bierman/hdf5_test.cbp
tests/projects/rob_joseph/hdf5_test.cbp
tests/projects/rob_ukf_bierman/hdf5_test.cbp
tests/projects/ukf/hdf5_test.cbp
tests/projects/ukf_bierman/hdf5_test.cbp
tests/src/ada_bierman.c
tests/src/ada_joseph.c
tests/src/ada_rob_bierman.c
tests/src/ada_rob_joseph.c
tests/src/ada_rob_ukf_bierman.c
tests/src/ada_ukf.c
tests/src/ada_ukf_bierman.c
tests/src/bierman.c
tests/src/create_h5.py
tests/src/hdf5utils.c
tests/src/hdf5utils.h
tests/src/imm.c
tests/src/joseph.c
tests/src/rob_bierman.c
tests/src/rob_joseph.c
tests/src/rob_ukf_bierman.c
tests/src/ukf.c
tests/src/ukf_bierman.c
tests/src/yaflpy_compile.py
tests/src/yaflpy_compile_robust.py
tests/src/yaflpy_compile_unscented.py
tests/src/yaflpy_compile_unscented_robust.py
tests/src/yaflpy_imm.py
tests/src/filterpy/UDEKF.py
tests/src/filterpy/UDEKHFPrior2.py
tests/src/filterpy/init_tests.py
tests/src/filterpy/testFilterpy01.py
tests/src/filterpy/testFilterpy02.py
tests/src/filterpy/testFilterpy03.py
yaflpy.egg-info/PKG-INFO
yaflpy.egg-info/SOURCES.txt
yaflpy.egg-info/dependency_links.txt
yaflpy.egg-info/not-zip-safe
yaflpy.egg-info/requires.txt
yaflpy.egg-info/top_level.txt