Metadata-Version: 2.1
Name: yaflpy
Version: 0.40.12
Summary: Yet Another Filtering Library
Home-page: https://github.com/shkolnick-kun/yafl
Author: anonimous
Author-email: shkolnick-kun@gmail.com
License: Apache License, Version 2.0
Project-URL: Documentation, https://github.com/shkolnick-kun/yafl
Project-URL: Code, https://github.com/shkolnick-kun/yafl
Project-URL: Issue tracker, https://github.com/shkolnick-kun/yafl/issues
Platform: any
Classifier: Development Status :: 3 - Alpha
Classifier: Intended Audience :: Science/Research
Classifier: Topic :: Scientific/Engineering
Classifier: Topic :: Scientific/Engineering :: Mathematics
Classifier: Topic :: Software Development :: Embedded Systems
Classifier: Natural Language :: English
Classifier: Operating System :: OS Independent
Classifier: Programming Language :: C
Classifier: Programming Language :: Cython
Classifier: Programming Language :: Python
Classifier: Programming Language :: Python :: 3
Classifier: Programming Language :: Python :: 3.9
Classifier: Programming Language :: Python :: 3.10
Classifier: Programming Language :: Python :: 3.11
Classifier: Programming Language :: Python :: 3 :: Only
Classifier: Programming Language :: Python :: Implementation :: CPython
Requires-Python: >=3.9
Provides-Extra: dev
Provides-Extra: docs
License-File: LICENSE
